image_processing_burato/__init__.py
image_processing_burato/processing/__init__.py
image_processing_burato/processing/combination.py
image_processing_burato/processing/transformation.py
image_processing_burato/utils/__init__.py
image_processing_burato/utils/io.py
image_processing_burato/utils/plot.py
image_processing_burato-0.0.2.dist-info/METADATA
image_processing_burato-0.0.2.dist-info/WHEEL
image_processing_burato-0.0.2.dist-info/top_level.txt
image_processing_burato-0.0.2.dist-info/RECORD
