Metadata-Version: 2.1
Name: image-processing-burato
Version: 0.0.2
Summary: Image processing package using skimage
Home-page: https://www.github.com/Otavio-Burato/image-processing-package
Author: Karina Tiemi
License: UNKNOWN
Platform: UNKNOWN
Requires-Python: >=3.5
Requires-Dist: matplotlib
Requires-Dist: numpy
Requires-Dist: scikit-image (>=0.16.1)
